{
    "keep": {
        "days": true,
        "amount": 14
    },
    "auditLog": "logs\\requests\\daily\\.66602cdde70fd43456e51d0c9addc83824638c4d-audit.json",
    "files": [
        {
            "date": 1649529368725,
            "name": "logs\\requests\\daily\\2022-04-10.log",
            "hash": "56f9fcd98c7b3c893249e7c9e594d06b"
        },
        {
            "date": 1649654374240,
            "name": "logs\\requests\\daily\\2022-04-11.log",
            "hash": "ec2ee2b9eaed9bee2d68e2bf5f0a8880"
        },
        {
            "date": 1649745791830,
            "name": "logs\\requests\\daily\\2022-04-12.log",
            "hash": "677b314d38829a56035cd790131317c7"
        },
        {
            "date": 1649830403573,
            "name": "logs\\requests\\daily\\2022-04-13.log",
            "hash": "7910ca4114b8982f10baf2daac11afbf"
        },
        {
            "date": 1649918643244,
            "name": "logs\\requests\\daily\\2022-04-14.log",
            "hash": "6562c8e0d39860ce7850a988d5d4a266"
        },
        {
            "date": 1650108898503,
            "name": "logs\\requests\\daily\\2022-04-16.log",
            "hash": "b015e045bac364575ea47981c97898e4"
        },
        {
            "date": 1650258647119,
            "name": "logs\\requests\\daily\\2022-04-18.log",
            "hash": "2fdaa20730f9fe376700a996cb5f87f6"
        },
        {
            "date": 1650355091223,
            "name": "logs\\requests\\daily\\2022-04-19.log",
            "hash": "3cbb2b8aa99c71ed83e304212dab12e6"
        },
        {
            "date": 1650432019616,
            "name": "logs\\requests\\daily\\2022-04-20.log",
            "hash": "5f0449640d1aac9a07ca638d1b7a1dd7"
        },
        {
            "date": 1650533582243,
            "name": "logs\\requests\\daily\\2022-04-21.log",
            "hash": "6830592912ace70fd49e63e6577745e3"
        },
        {
            "date": 1650627320000,
            "name": "logs\\requests\\daily\\2022-04-22.log",
            "hash": "851c77c87e9b07977849cde329141b51"
        },
        {
            "date": 1650708460693,
            "name": "logs\\requests\\daily\\2022-04-23.log",
            "hash": "b01d50be51a5ebc088f37d59bcddb821"
        }
    ],
    "hashType": "md5"
}